{
    "slug": "interacting-with-apis-for-beginners",
    "title": {
        "us": "API and Complex JSON Navigation",
        "es": "API y Navegaci\u00f3n de JSON Complejo"
    },
    "description": {
        "us": "Practice RESTful API interactions with POST, PUT, PATCH, DELETE, and follow-up GET requests using JavaScript.",
        "es": "Practica interacciones RESTful con APIs usando POST, PUT, PATCH, DELETE y consultas posteriores con GET en JavaScript."
    },
    "preview": "https://github.com/4GeeksAcademy/interacting-with-apis-for-beginners/blob/main/preview.png?raw=true",
    "difficulty": "EASY",
    "duration": 8,
    "template_url": null,
    "gitpod": true,
    "technologies": [
        "javascript",
        "json",
        "rest-api",
        "fetch-api",
        "HTTP",
        "crud"
    ],
    "projectType": "tutorial",
    "editor": {
        "agent": "vscode"
    },
    "grading": "incremental",
    "localhostOnly": false,
    "delivery": {
        "instructions": "",
        "formats": [
            "no_delivery"
        ],
        "regex": ""
    }
}